main.py
pytest_inline_snapshot-0.1.1.dist-info/METADATA
pytest_inline_snapshot-0.1.1.dist-info/WHEEL
pytest_inline_snapshot-0.1.1.dist-info/top_level.txt
pytest_inline_snapshot-0.1.1.dist-info/RECORD
