Metadata-Version: 2.4
Name: pytest-inline-snapshot
Version: 0.1.1
Summary: inline-snapshot is the package you are looking for
Requires-Python: >=3.14
